orf_utils/__init__.py
orf_utils/check_submodule_commits.py
orf_utils/check_version.py
orf_utils/common.py
orf_utils/get_team_approval_status.py
orf_utils/metadata.json
orf_utils/py.typed
orf_utils/tag_commit.py
orf_utils/mocks/__init__.py
orf_utils/mocks/gitpython_utils.py
orf_utils/mocks/pygithub_utils.py
orf_utils-0.1.0.dist-info/LICENSE
orf_utils-0.1.0.dist-info/METADATA
orf_utils-0.1.0.dist-info/WHEEL
orf_utils-0.1.0.dist-info/entry_points.txt
orf_utils-0.1.0.dist-info/top_level.txt
orf_utils-0.1.0.dist-info/RECORD
