Metadata-Version: 2.1
Name: orf-utils
Version: 0.1.0
Summary: Utils for different actions within the open-reading-frame GitHub Organization
Classifier: Programming Language :: Python
Classifier: Programming Language :: Python :: 3
Classifier: Programming Language :: Python :: 3.10
Classifier: Programming Language :: Python :: 3.11
Classifier: Operating System :: OS Independent
License-File: LICENSE
Requires-Dist: PyGithub
Requires-Dist: GitPython
Requires-Dist: ghapi
